AirAlerts/__init__.py
AirAlerts/async.py
AirAlerts/sync.py
AirAlerts/test.py
AirAlerts-1.0.3.dist-info/LICENSE.TXT
AirAlerts-1.0.3.dist-info/METADATA
AirAlerts-1.0.3.dist-info/WHEEL
AirAlerts-1.0.3.dist-info/top_level.txt
AirAlerts-1.0.3.dist-info/RECORD
