Metadata-Version: 2.1
Name: AirAlerts
Version: 1.0.3
Summary: A Python module for monitoring Air Raid Alerts in Ukraine
Author: Romikan
Author-email: romikan.code@gmail.com
Classifier: Development Status :: 2 - Pre-Alpha
Classifier: Intended Audience :: Developers
Classifier: Topic :: Utilities
Classifier: License :: OSI Approved :: MIT License
Classifier: Programming Language :: Python :: 3
Classifier: Programming Language :: Python :: 3.6
Classifier: Programming Language :: Python :: 3.7
Classifier: Programming Language :: Python :: 3.8
Classifier: Programming Language :: Python :: 3.9
License-File: LICENSE.TXT
Requires-Dist: requests
Requires-Dist: pillow
